cap_gen-0.1.0.dist-info/METADATA
cap_gen-0.1.0.dist-info/WHEEL
cap_gen/__init__.py
cap_gen/__init__.pyi
cap_gen/py.typed
cap_gen/cap_gen.cpython-312-x86_64-linux-gnu.so
cap_gen-0.1.0.dist-info/RECORD
