Metadata-Version: 2.3
Name: cap-gen
Version: 0.1.0
Classifier: Development Status :: 4 - Beta
Classifier: Intended Audience :: Developers
Classifier: License :: OSI Approved :: MIT License
Classifier: Programming Language :: Python
Classifier: Programming Language :: Python :: 3
Classifier: Programming Language :: Python :: 3.9
Classifier: Programming Language :: Python :: 3.10
Classifier: Programming Language :: Python :: 3.11
Classifier: Programming Language :: Python :: 3.12
Classifier: Operating System :: OS Independent
Classifier: Topic :: Software Development :: Libraries
Classifier: Topic :: Internet :: WWW/HTTP
Summary: 🚀 Lightweight Captcha Generator for 🐍 Python
Keywords: captcha,telegram,authentication,auth,python,bot,security,rust
Author-email: vffuunnyy <vffuunnyy@gmail.com>
License: MIT
Requires-Python: >=3.9.0
Project-URL: Homepage, https://github.com/vffuunnyy/captcha_generator/
Project-URL: Documentation, https://github.com/vffuunnyy/captcha_generator/
Project-URL: Repository, https://github.com/vffuunnyy/captcha_generator.git
Project-URL: Issues, https://github.com/vffuunnyy/captcha_generator/issues
